EnginML/__init__.py
EnginML/cli.py
EnginML/core.py
EnginML/explain.py
EnginML/report.py
enginml-0.1.3.dist-info/licenses/LICENSE
enginml-0.1.3.dist-info/METADATA
enginml-0.1.3.dist-info/WHEEL
enginml-0.1.3.dist-info/entry_points.txt
enginml-0.1.3.dist-info/top_level.txt
enginml-0.1.3.dist-info/RECORD
