Metadata-Version: 2.4
Name: EnginML
Version: 0.1.3
Summary: Guided baseline ML workflows (regression / classification / clustering) for engineers
Author-email: Amir Rafe <amir.rafe@usu.edu>
License: MIT
Project-URL: Homepage, https://github.com/pozapas/EnginML
Project-URL: Repository, https://github.com/pozapas/EnginML
Keywords: machine-learning,scikit-learn,explainability
Classifier: Programming Language :: Python :: 3
Classifier: License :: OSI Approved :: MIT License
Classifier: Intended Audience :: Science/Research
Classifier: Topic :: Scientific/Engineering :: Artificial Intelligence
Requires-Python: >=3.9
License-File: LICENSE
Requires-Dist: numpy>=1.20.0
Requires-Dist: pandas>=1.3.0
Requires-Dist: scikit-learn>=1.0.0
Requires-Dist: matplotlib>=3.4.0
Provides-Extra: full
Requires-Dist: xgboost>=2.0.0; extra == "full"
Requires-Dist: shap>=0.40.0; extra == "full"
Requires-Dist: jinja2>=3.0.0; extra == "full"
Dynamic: license-file
